lab1_basic/c.v
module and2(input wire i0, i1, output wire o2);
	assign o2 = i0 & i1;
endmodule

module or2(input wire i0, i1, output wire o3);
	assign o3 = i0 | i1;
endmodule


module operate(input wire a,b,c, output wire z);
	wire t0,t1;
	and2 and2_0(a,b,t0);
	and2 and2_1(b,c,t1);
	or2 or2_0(t0,t1,z);
endmodule

lab1_basic/ctestbench.v
module tb;
reg t_a;
reg t_b;
reg t_c;
wire T;
//instantiate

//and2 a2(.i0(t_a),.i1(t_b),.o2(Q));
//and2 a2(.i0(t_a),.i1(t_b),.o2(Q));
//or2 a3(.i0(t_a),.i1(t_b),.o3(R));
operate a4(.a(t_a),.b(t_b),.c(t_c),.z(T));

initial begin $dumpfile("dmp2.vcd");
$dumpvars(0,tb);
end
initial begin $monitor(t_a,t_b,t_c,T); //displays the content of the register
t_a=1'b0;//1 bit input
t_b=1'b0;
t_c=1'b0;
#10 //time nanosecs
t_a=1'b0;//1 bit input
t_b=1'b0;
t_c=1'b1;
#10 //time nanosecs
t_a=1'b0;//1 bit input
t_b=1'b1;
t_c=1'b0;
#10 //time nanosecs
t_a=1'b0;//1 bit input
t_b=1'b1;
t_c=1'b1;
#10 //time nanosecs
t_a=1'b1;//1 bit input
t_b=1'b0;
t_c=1'b0;
#10 //time nanosecs
t_a=1'b1;//1 bit input
t_b=1'b0;
t_c=1'b1;
#10 //time nanosecs
t_a=1'b1;//1 bit input
t_b=1'b1;
t_c=1'b0;
#10 //time nanosecs
t_a=1'b1;//1 bit input
t_b=1'b1;
t_c=1'b1;
#10 //time nanosecs

t_a=0;//inorder to see the last input
t_b=0;
t_b=0;
end
endmodule

lab1_basic/dmp2.vcd
$date
	Thu Sep 23 08:09:44 2021
$end
$version
	Icarus Verilog
$end
$timescale
	1s
$end
$scope module tb $end
$var wire 1 ! T $end
$var reg 1 " t_a $end
$var reg 1 # t_b $end
$var reg 1 $ t_c $end
$scope module a4 $end
$var wire 1 " a $end
$var wire 1 # b $end
$var wire 1 $ c $end
$var wire 1 ! z $end
$var wire 1 % t1 $end
$var wire 1 & t0 $end
$scope module and2_0 $end
$var wire 1 " i0 $end
$var wire 1 # i1 $end
$var wire 1 & o2 $end
$upscope $end
$scope module and2_1 $end
$var wire 1 # i0 $end
$var wire 1 $ i1 $end
$var wire 1 % o2 $end
$upscope $end
$scope module or2_0 $end
$var wire 1 & i0 $end
$var wire 1 % i1 $end
$var wire 1 ! o3 $end
$upscope $end
$upscope $end
$upscope $end
$enddefinitions $end
#0
$dumpvars
0&
0%
0$
0#
0"
0!
$end
#10
1$
#20
0$
1#
#30
1!
1%
1$
#40
0!
0%
0$
0#
1"
#50
1$
#60
1!
1&
0$
1#
#70
1%
1$
#80
0!
0%
0&
0#
0"
